guess_my_number_dude/__init__.py
guess_my_number_dude/main.py
guess_my_number_dude-0.0.1.dist-info/METADATA
guess_my_number_dude-0.0.1.dist-info/WHEEL
guess_my_number_dude-0.0.1.dist-info/top_level.txt
guess_my_number_dude-0.0.1.dist-info/RECORD
