Metadata-Version: 2.1
Name: guess-my-number-dude
Version: 0.0.1
Summary: Package for test
Home-page: http://bitbucket.org/dude/distribute/issues/
Author: Yury Herasimau
Author-email: dude@mail.ru
License: UNKNOWN
Platform: UNKNOWN
Classifier: Programming Language :: Python :: 3.8
Classifier: License :: OSI Approved :: MIT License
Classifier: Operating System :: OS Independent
Requires-Python: >=3.8
